openfret/__init__.py
openfret/openfret.py
openfret-0.1.1.dist-info/LICENSE
openfret-0.1.1.dist-info/METADATA
openfret-0.1.1.dist-info/WHEEL
openfret-0.1.1.dist-info/top_level.txt
openfret-0.1.1.dist-info/RECORD
