Metadata-Version: 2.1
Name: openfret
Version: 0.1.1
Summary: A standardized format for single-molecule FRET data
Author-email: Jieming Li <jmli@umich.edu>, Leyou Zhang <leyou@umich.edu>
License: MIT License
Project-URL: Homepage, https://github.com/simol-lab/OpenFRET
Project-URL: Bug Tracker, https://github.com/simol-lab/OpenFRET/issues
Classifier: Programming Language :: Python :: 3
Classifier: License :: OSI Approved :: MIT License
Classifier: Operating System :: OS Independent
Classifier: Topic :: Scientific/Engineering :: Bio-Informatics
Classifier: Topic :: Scientific/Engineering :: Physics
Classifier: Intended Audience :: Science/Research
License-File: LICENSE
